odoo/addons/mrp_operating_unit/README.rst
odoo/addons/mrp_operating_unit/__init__.py
odoo/addons/mrp_operating_unit/__manifest__.py
odoo/addons/mrp_operating_unit/i18n/it.po
odoo/addons/mrp_operating_unit/i18n/mrp_operating_unit.pot
odoo/addons/mrp_operating_unit/models/__init__.py
odoo/addons/mrp_operating_unit/models/mrp.py
odoo/addons/mrp_operating_unit/models/stock_rule.py
odoo/addons/mrp_operating_unit/readme/CONTRIBUTORS.md
odoo/addons/mrp_operating_unit/readme/DESCRIPTION.md
odoo/addons/mrp_operating_unit/readme/USAGE.md
odoo/addons/mrp_operating_unit/security/mrp_security.xml
odoo/addons/mrp_operating_unit/static/description/icon.png
odoo/addons/mrp_operating_unit/static/description/index.html
odoo/addons/mrp_operating_unit/tests/__init__.py
odoo/addons/mrp_operating_unit/tests/test_mrp_operating_unit.py
odoo/addons/mrp_operating_unit/views/mrp_view.xml
odoo_addon_mrp_operating_unit-18.0.1.0.0.4.dist-info/METADATA
odoo_addon_mrp_operating_unit-18.0.1.0.0.4.dist-info/WHEEL
odoo_addon_mrp_operating_unit-18.0.1.0.0.4.dist-info/top_level.txt
odoo_addon_mrp_operating_unit-18.0.1.0.0.4.dist-info/RECORD
