Metadata-Version: 2.1
Name: odoo-addon-mrp_operating_unit
Version: 18.0.1.0.0.4
Requires-Python: >=3.10
Requires-Dist: odoo-addon-stock_operating_unit==18.0.*
Requires-Dist: odoo==18.0.*
Summary: Operating Unit in MRP
Home-page: https://github.com/OCA/operating-unit
License: LGPL-3
Author: Odoo Community Association (OCA)
Author-email: support@odoo-community.org
Classifier: Programming Language :: Python
Classifier: Framework :: Odoo
Classifier: Framework :: Odoo :: 18.0
Classifier: License :: OSI Approved :: GNU Lesser General Public License v3 (LGPLv3)
